lidario/__init__.py
lidario/translator.py
lidario-0.1.0.dist-info/METADATA
lidario-0.1.0.dist-info/WHEEL
lidario-0.1.0.dist-info/top_level.txt
lidario-0.1.0.dist-info/RECORD
