Metadata-Version: 2.1
Name: lidario
Version: 0.1.0
Summary: High-level toolbox to manipulate LIDAR raster and point cloud
Home-page: https://github.com/joffreybvn/lidario
Author: Joffrey Bienvenu
Author-email: joffreybvn@gmail.com
License: MIT
Platform: UNKNOWN
Classifier: Intended Audience :: Developers
Classifier: Intended Audience :: Science/Research
Classifier: License :: OSI Approved :: MIT License
Classifier: Programming Language :: Python
Classifier: Programming Language :: Python :: 2
Classifier: Programming Language :: Python :: 2.7
Classifier: Programming Language :: Python :: 3
Classifier: Programming Language :: Python :: 3.6
Classifier: Programming Language :: Python :: 3.7
Classifier: Programming Language :: Python :: 3.8
Classifier: Programming Language :: Python :: 3.9
Classifier: Operating System :: OS Independent
Classifier: Topic :: Scientific/Engineering :: GIS
Classifier: Topic :: Utilities
Requires-Dist: pandas
Requires-Dist: numpy
Requires-Dist: rasterio
